mellori/__init__.py
mellori-0.0.1.dev1.dist-info/METADATA
mellori-0.0.1.dev1.dist-info/RECORD
mellori-0.0.1.dev1.dist-info/WHEEL
mellori-0.0.1.dev1.dist-info/top_level.txt
