Metadata-Version: 2.1
Name: mellori
Version: 0.0.1.dev1
Summary: Mellori
Home-page: https://github.com/lodek/mellori
Author: Lodek
Author-email: lodek@protonmail.com
License: UNKNOWN
Platform: UNKNOWN
